{
  "type": "mysticalagriculture:infusion",
  "conditions": [
    {
      "type": "mysticalagriculture:crop_enabled",
      "crop": "mysticalagriculture:skeleton"
    },
    {
      "type": "mysticalagriculture:crop_has_material",
      "crop": "mysticalagriculture:skeleton"
    }
  ],
  "input": {
    "component": "seed",
    "crop": "skeleton"
  },
  "ingredients": [
    {
      "component": "material",
      "crop": "skeleton"
    },
    {
      "component": "essence",
      "crop": "skeleton"
    },
    {
      "component": "material",
      "crop": "skeleton"
    },
    {
      "component": "essence",
      "crop": "skeleton"
    },
    {
      "component": "material",
      "crop": "skeleton"
    },
    {
      "component": "essence",
      "crop": "skeleton"
    },
    {
      "component": "material",
      "crop": "skeleton"
    },
    {
      "component": "essence",
      "crop": "skeleton"
    }
  ],
  "result": {
    "item": "mysticalagriculture:skeleton_seeds"
  }
}